
{
    "newsChannelId": 
    {
        "bot":
        {
            "allow": 
            [
                "USE_EXTERNAL_EMOJIS", 
                "MENTION_EVERYONE", 
                "SEND_TTS_MESSAGES", 
                "VIEW_CHANNEL", 
                "SEND_MESSAGES", 
                "MANAGE_MESSAGES", 
                "EMBED_LINKS", 
                "ATTACH_FILES"
            ],
            "deny": []
        },

        "members":
        {
            "allow": 
            [
                "VIEW_CHANNEL",
                "READ_MESSAGE_HISTORY"
            ],
            "deny": 
            [
                "USE_EXTERNAL_EMOJIS", 
                "MENTION_EVERYONE", 
                "SEND_TTS_MESSAGES", 
                "VIEW_CHANNEL", 
                "SEND_MESSAGES", 
                "MANAGE_MESSAGES", 
                "EMBED_LINKS", 
                "ATTACH_FILES",
                "ADD_REACTIONS"
            ]
        }
    },

    "helpChannelId":  
    {
        "bot":
        {
            "allow": 
            [
                "USE_EXTERNAL_EMOJIS", 
                "MENTION_EVERYONE", 
                "SEND_TTS_MESSAGES", 
                "VIEW_CHANNEL", 
                "SEND_MESSAGES", 
                "MANAGE_MESSAGES", 
                "EMBED_LINKS", 
                "ATTACH_FILES"
            ],
            "deny": []
        },

        "members":
        {
            "allow": 
            [
                "VIEW_CHANNEL",
                "READ_MESSAGE_HISTORY"
            ],
            "deny": 
            [
                "USE_EXTERNAL_EMOJIS", 
                "MENTION_EVERYONE", 
                "SEND_TTS_MESSAGES", 
                "VIEW_CHANNEL", 
                "SEND_MESSAGES", 
                "MANAGE_MESSAGES", 
                "EMBED_LINKS", 
                "ATTACH_FILES",
                "ADD_REACTIONS"
            ]
        }
    },

    "recruitingCategoryId":  
    {
        "bot":
        {
            "allow": [],
            "deny": []
        },

        "members":
        {
            "allow": [],
            "deny": []
        }
    },
    
    "blitzRecruitingCategoryId":  
    {
        "bot":
        {
            "allow": [],
            "deny": []
        },

        "members":
        {
            "allow": [],
            "deny": []
        }
    },
    
    "gameCategoryId":  
    {
        "bot":
        {
            "allow": [],
            "deny": []
        },

        "members":
        {
            "allow": [],
            "deny": []
        }
    },
    
    "blitzCategoryId":  
    {
        "bot":
        {
            "allow": [],
            "deny": []
        },

        "members":
        {
            "allow": [],
            "deny": []
        }
    },
    
    "blitzerRoleId":  [],
    "gameMasterRoleId": [],
    "trustedRoleId": []
}